fullscreen/__init__.py
fullscreen/core - 副本.py
fullscreen/core.py
fullscreen_alert-0.1.3.dist-info/licenses/LICENSE
fullscreen_alert-0.1.3.dist-info/METADATA
fullscreen_alert-0.1.3.dist-info/WHEEL
fullscreen_alert-0.1.3.dist-info/top_level.txt
fullscreen_alert-0.1.3.dist-info/RECORD
